<?xml version="1.0" encoding="utf-8" ?>
<!--============================================================================
//	CAUTION: This file is generated by BatisMap.cst at 2010-09-26 13:53:26
//				Any manual editing will be lost in re-generation.
//===========================================================================-->
<sqlMap namespace="Sys_Role"
	xmlns="http://ibatis.apache.org/mapping"
	xmlns:xsi="http://www.w3.org/2001/XMLSchema-instance">

    <alias>
        <!--###Please Edit type by yourself###-->
        <typeAlias alias="Sys_Role" type="KingSite.Purview.Domain.Sys_Role, KingSite.Purview" />
    </alias>

    <resultMaps>
        <resultMap id="FullResultMap" class="Sys_Role">
            <result property="Id" column="Id"/>
            <result property="ApplicationName" column="ApplicationName"/>
            <result property="RoleName" column="RoleName"/>
        </resultMap>
    </resultMaps>

    <statements>

        <select id="GetCount" resultClass="System.Int32">
            SELECT count(*) FROM sys_role
        </select>

        <select id="FindAll" resultMap="FullResultMap">
            SELECT *
            FROM sys_role
        </select>


        <select id="Find" parameterClass="Int32" resultMap="FullResultMap" extends="FindAll">
            WHERE
            Id = #Id#
        </select>

        <select id="FindByName" parameterClass="Sys_Role" resultMap="FullResultMap" extends="FindAll">
            WHERE
            Rolename = #RoleName# AND ApplicationName = #ApplicationName#
        </select>

        <select id="GetAllRole" parameterClass="Sys_Role" resultMap="FullResultMap" extends="FindAll">
            WHERE
            ApplicationName = #ApplicationName#
        </select>

        <update id="Insert" parameterClass="Sys_Role">
            INSERT INTO sys_role (
            ApplicationName
            , RoleName
            ) VALUES (
            #ApplicationName#
            , #RoleName#
            )
        </update>

        <update id="Update" parameterClass="Sys_Role">
            UPDATE sys_role SET
            ApplicationName = #ApplicationName#
            , RoleName = #RoleName#
            WHERE
            Id = #Id#
        </update>

        <delete id="Delete" parameterClass="Int32">
            DELETE FROM sys_role
            WHERE
            Id = #Id#
        </delete>

        <update id="DeleteByName" parameterClass="Sys_Role">
            DELETE FROM sys_role
            WHERE
            ApplicationName = #ApplicationName# and RoleName = #RoleName#;

            DELETE FROM sys_userinrole
            WHERE
            ApplicationName = #ApplicationName# and RoleName = #RoleName#;
        </update>

    </statements>
</sqlMap>
